firstposts/__init__.py
firstposts/firstposts.py
firstposts-0.1.data/scripts/firstposts.py
firstposts-0.1.dist-info/DESCRIPTION.rst
firstposts-0.1.dist-info/METADATA
firstposts-0.1.dist-info/RECORD
firstposts-0.1.dist-info/WHEEL
firstposts-0.1.dist-info/metadata.json
firstposts-0.1.dist-info/top_level.txt
