Metadata-Version: 2.0
Name: firstposts
Version: 0.1
Summary: Find Subreddit Firstposts
Home-page: https://github.com/gusberinger/firstposts
Author: Gus Beringer
Author-email: gusberinger@gmail.com
License: MIT
Keywords: reddit
Platform: UNKNOWN
Classifier: Intended Audience :: Developers
Classifier: Topic :: Internet
Requires-Dist: praw
Requires-Dist: pyYAML
